{
  "items": [
    { "id": 1, "name": "George Washington" },
    { "id": 2, "name": "John Adams" },
    { "id": 3, "name": "Thomas Jefferson" },
    { "id": 4, "name": "James Madison" },
    { "id": 5, "name": "James Monroe" },
    { "id": 6, "name": "John Quincy Adams" },
    { "id": 7, "name": "Andrew Jackson" },
    { "id": 8, "name": "Martin Van Buren" },
    { "id": 9, "name": "William Henry Harrison" },
    { "id": 10, "name": "John Tyler" },
    { "id": 11, "name": "James Knox Polk" },
    { "id": 12, "name": "Zachary Taylor" },
    { "id": 13, "name": "Millard Fillmore" },
    { "id": 14, "name": "Franklin Pierce" },
    { "id": 15, "name": "James Buchanan" },
    { "id": 16, "name": "Abraham Lincoln" },
    { "id": 17, "name": "Andrew Johnson" },
    { "id": 18, "name": "Ulysses S. Grant" },
    { "id": 19, "name": "Rutherford B. Hayes" },
    { "id": 20, "name": "James A. Garfield" },
    { "id": 21, "name": "Chester A. Arthur" },
    { "id": 22, "name": "Grover Cleveland" },
    { "id": 23, "name": "Benjamin Harrison" },
    { "id": 24, "name": "Grover Cleveland" },
    { "id": 25, "name": "William McKinley" },
    { "id": 26, "name": "Theodore Roosevelt" },
    { "id": 27, "name": "William Howard Taft" },
    { "id": 28, "name": "Woodrow Wilson" },
    { "id": 29, "name": "Warren G. Harding" },
    { "id": 30, "name": "Calvin Coolidge" },
    { "id": 31, "name": "Herbert Hoover" },
    { "id": 32, "name": "Franklin D. Roosevelt" },
    { "id": 33, "name": "Harry S. Truman" },
    { "id": 34, "name": "Dwight D. Eisenhower" },
    { "id": 35, "name": "John F. Kennedy" },
    { "id": 36, "name": "Lyndon B. Johnson" },
    { "id": 37, "name": "Richard Nixon" },
    { "id": 38, "name": "Gerald Ford" },
    { "id": 39, "name": "Jimmy Carter" },
    { "id": 40, "name": "Ronald Reagan" },
    { "id": 41, "name": "George H. W. Bush" },
    { "id": 42, "name": "Bill Clinton" },
    { "id": 43, "name": "George W. Bush" },
    { "id": 44, "name": "Barack Obama" },
    { "id": 45, "name": "Donald Trump" },
    { "id": 46, "name": "Joe Biden" }
  ]
}
